gallagher/__init__.py
gallagher/const.py
gallagher/decorators.py
gallagher/enum.py
gallagher/exception.py
gallagher/cc/__init__.py
gallagher/cc/access_groups.py
gallagher/cc/core.py
gallagher/cc/doors.py
gallagher/cc/lockers.py
gallagher/cc/operators.py
gallagher/cc/receptions.py
gallagher/cc/roles.py
gallagher/cc/visitors.py
gallagher/cc/visits.py
gallagher/cc/zones.py
gallagher/cc/alarms/__init__.py
gallagher/cc/alarms/day_category.py
gallagher/cc/alarms/divisions.py
gallagher/cc/alarms/events.py
gallagher/cc/alarms/items.py
gallagher/cc/alarms/schedule.py
gallagher/cc/cardholders/__init__.py
gallagher/cc/cardholders/card_type.py
gallagher/cc/status_overrides/__init__.py
gallagher/cli/__init__.py
gallagher/cli/access_groups.py
gallagher/cli/agroup.py
gallagher/cli/alarms.py
gallagher/cli/azone.py
gallagher/cli/cardholders.py
gallagher/cli/comp.py
gallagher/cli/const.py
gallagher/cli/day.py
gallagher/cli/divisions.py
gallagher/cli/door.py
gallagher/cli/doors.py
gallagher/cli/elevator.py
gallagher/cli/events.py
gallagher/cli/fence.py
gallagher/cli/ilock.py
gallagher/cli/input.py
gallagher/cli/item.py
gallagher/cli/locker.py
gallagher/cli/lockers.py
gallagher/cli/macro.py
gallagher/cli/og.py
gallagher/cli/operators.py
gallagher/cli/output.py
gallagher/cli/pdf.py
gallagher/cli/reception.py
gallagher/cli/receptions.py
gallagher/cli/redaction.py
gallagher/cli/roles.py
gallagher/cli/schedule.py
gallagher/cli/utils.py
gallagher/cli/visitors.py
gallagher/cli/visits.py
gallagher/cli/zones.py
gallagher/dto/__init__.py
gallagher/dto/enum.py
gallagher/dto/utils.py
gallagher/dto/detail/__init__.py
gallagher/dto/detail/access_group.py
gallagher/dto/detail/alarm.py
gallagher/dto/detail/card.py
gallagher/dto/detail/card_type.py
gallagher/dto/detail/cardholder.py
gallagher/dto/detail/day_category.py
gallagher/dto/detail/discover.py
gallagher/dto/detail/division.py
gallagher/dto/detail/door.py
gallagher/dto/detail/event.py
gallagher/dto/detail/features.py
gallagher-1.0.0a16.dist-info/METADATA
gallagher-1.0.0a16.dist-info/WHEEL
gallagher-1.0.0a16.dist-info/entry_points.txt
gallagher-1.0.0a16.dist-info/licenses/LICENSE
gallagher-1.0.0a16.dist-info/RECORD
