Metadata-Version: 2.4
Name: gallagher
Version: 1.0.0a16
Summary: The missing developer toolkit for Gallagher Command Centre
Author-email: Anomaly <oss@anomaly.ltd>
License: MIT
License-File: LICENSE
Requires-Python: >=3.12
Requires-Dist: email-validator>=2.2.0
Requires-Dist: httpx<0.29.0,>=0.28.1
Requires-Dist: pydantic<3.0.0,>=2.11.5
Provides-Extra: cli
Requires-Dist: typer<1.0.0,>=0.16.0; extra == 'cli'
Provides-Extra: dev
Requires-Dist: mkdocs-material<10.0.0,>=9.6.14; extra == 'dev'
Requires-Dist: mkdocs-typer<1.0.0,>=0.0.3; extra == 'dev'
Requires-Dist: mkdocs<2.0.0,>=1.6.1; extra == 'dev'
Requires-Dist: pygments<3.0.0,>=2.19.1; extra == 'dev'
Requires-Dist: pytest-order<2.0.0,>=1.3.0; extra == 'dev'
Requires-Dist: pytest<9.0.0,>=8.3.5; extra == 'dev'
Requires-Dist: textual-dev<2.0.0,>=1.7.0; extra == 'dev'
Provides-Extra: sync
Requires-Dist: alembic<2.0.0,>=1.16.1; extra == 'sync'
Requires-Dist: shillelagh<2.0.0,>=1.3.5; extra == 'sync'
Requires-Dist: sqlalchemy<3.0.0,>=2.0.41; extra == 'sync'
Provides-Extra: tui
Requires-Dist: textual<4.0.0,>=3.2.0; extra == 'tui'
